file_cycle.py
FileCycle_nachash-0.0.1.dist-info/LICENSE
FileCycle_nachash-0.0.1.dist-info/METADATA
FileCycle_nachash-0.0.1.dist-info/WHEEL
FileCycle_nachash-0.0.1.dist-info/top_level.txt
FileCycle_nachash-0.0.1.dist-info/RECORD
