Metadata-Version: 2.1
Name: FileCycle_nachash
Version: 0.0.1
Summary: The FileCycle is a Python library designed to manage file rotation in a specified directory. 
Author-email: Bo Stokholm <the.one.nachash@gmail.com>
Project-URL: Homepage, https://github.com/pypa/sampleproject
Project-URL: Bug Tracker, https://github.com/pypa/sampleproject/issues
Classifier: Programming Language :: Python :: 3
Classifier: License :: OSI Approved :: MIT License
Classifier: Operating System :: OS Independent
Requires-Python: >=3.7
License-File: LICENSE
